tilebatch/__init__.py
tilebatch/__main__.py
tilebatch/batch.py
tilebatch/utils.py
emtilebatch-0.1.3.dist-info/METADATA
emtilebatch-0.1.3.dist-info/WHEEL
emtilebatch-0.1.3.dist-info/top_level.txt
emtilebatch-0.1.3.dist-info/RECORD
