Metadata-Version: 2.1
Name: emtilebatch
Version: 0.1.3
Summary: Python package of the EM data Tile Batch script
Home-page: https://github.com/mpicbg-scicomp
Author: HongKee Moon
Author-email: moon@mpi-cbg.de
License: BSD
Platform: UNKNOWN
Classifier: Development Status :: 1 - Planning
Classifier: Intended Audience :: Science/Research
Classifier: License :: OSI Approved :: BSD License
Classifier: Operating System :: POSIX :: Linux
Classifier: Programming Language :: Python :: 3
Classifier: Programming Language :: Python :: 3.9
